pygraid/__init__.py
pygraid/data/anim.csv
pygraid/data/boundaries.csv
pygraid/data/pred.csv
pygraid/data/ref.csv
pygraid/data/syn.csv
pygraid-0.1.0.dist-info/LICENSE
pygraid-0.1.0.dist-info/METADATA
pygraid-0.1.0.dist-info/WHEEL
pygraid-0.1.0.dist-info/entry_points.txt
pygraid-0.1.0.dist-info/RECORD
